Alapchari/__init__.py
Alapchari-1.0.0.dist-info/LICENSE
Alapchari-1.0.0.dist-info/METADATA
Alapchari-1.0.0.dist-info/WHEEL
Alapchari-1.0.0.dist-info/top_level.txt
Alapchari-1.0.0.dist-info/RECORD
