Metadata-Version: 2.1
Name: Alapchari
Version: 1.0.0
Summary: Lets you interact with the Alapchari Chatbot.
Home-page: https://github.com/NurTasin/Alapchari-Python
Author: Nur Mahmud Ul Alam Tasin
Author-email: nmuatasin2005@gmail.com
License: MIT License
Platform: x86
Platform: x86_64
Platform: arm
Classifier: License :: OSI Approved :: MIT License
Classifier: Programming Language :: Python :: 3
Classifier: Programming Language :: Python :: 3.6
Classifier: Programming Language :: Python :: 3.7
Classifier: Programming Language :: Python :: 3.8
Classifier: Programming Language :: Python :: 3.9
Classifier: Operating System :: OS Independent
License-File: LICENSE
Requires-Dist: requests
